seqscore/__init__.py
seqscore/conll.py
seqscore/encoding.py
seqscore/model.py
seqscore/processing.py
seqscore/scoring.py
seqscore/util.py
seqscore/validation.py
seqscore/scripts/__init__.py
seqscore/scripts/seqscore.py
seqscore-0.7.0.dist-info/licenses/LICENSE
seqscore-0.7.0.dist-info/METADATA
seqscore-0.7.0.dist-info/WHEEL
seqscore-0.7.0.dist-info/entry_points.txt
seqscore-0.7.0.dist-info/top_level.txt
seqscore-0.7.0.dist-info/RECORD
